Metadata-Version: 1.0
Name: gojson
Version: 1.2.0
Summary: A python library for https://db.neelr.dev/
Home-page: https://github.com/AgeOfMarcus/gojson
Author: AgeOfMarcus
Author-email: marcus@marcusweinberger.com
License: UNKNOWN
Platform: UNKNOWN
